neurodeploy/__init__.py
neurodeploy-0.1.3.dist-info/METADATA
neurodeploy-0.1.3.dist-info/WHEEL
neurodeploy-0.1.3.dist-info/licenses/LICENSE
neurodeploy-0.1.3.dist-info/RECORD
